PandaPrimes-0.0.6.dist-info/METADATA
PandaPrimes-0.0.6.dist-info/top_level.txt
PandaPrimes-0.0.6.dist-info/WHEEL
PandaPrimes-0.0.6.dist-info/RECORD
PandaPrimes/PandaPrimes.pyi
PandaPrimes/__init__.py
PandaPrimes/PandaPrimes.cpython-39-x86_64-linux-gnu.so
PandaPrimes/src/include/primes-range.h
PandaPrimes/src/include/generate-primes.h
PandaPrimes/src/include/iterator.h
