Metadata-Version: 2.1
Name: PandaPrimes
Version: 0.0.6
Summary: A Python extension module for finding primes using C
Author: PaNDa2code
Author-email: moaaz0688@gmail.com
Project-URL: Source, https://github.com/PaNDa2code/PandaPrimes
Requires-Dist: setuptools
Requires-Dist: numpy
Requires-Dist: cmake
